unstdlibpy/__init__.py
unstdlibpy/algebra.py
unstdlibpy/algo.py
unstdlibpy/const.py
unstdlibpy/hlambda.py
unstdlibpy/math.py
unstdlibpy/random.py
unstdlibpy/random_old.py
unstdlibpy/save.py
unstdlibpy/universal.py
unstdlibpy-0.1.0.0.5.dist-info/METADATA
unstdlibpy-0.1.0.0.5.dist-info/WHEEL
unstdlibpy-0.1.0.0.5.dist-info/RECORD
