Metadata-Version: 2.4
Name: unstdlibpy
Version: 0.1.0.0.5
Summary: A ligntweight package
License: MIT
Keywords: utility,library,python,helpers,tools
Author: Chen Yuxuan
Author-email: null_3@qq.com
Requires-Python: >=3.10,<4.0
Classifier: License :: OSI Approved :: MIT License
Classifier: Programming Language :: Python :: 3
Classifier: Programming Language :: Python :: 3.10
Classifier: Programming Language :: Python :: 3.11
Classifier: Programming Language :: Python :: 3.12
Classifier: Programming Language :: Python :: 3.13
Classifier: Programming Language :: Python :: 3.14
